MANIFEST.in
README.rst
setup.py
goldfinch/__init__.py
goldfinch.egg-info/PKG-INFO
goldfinch.egg-info/SOURCES.txt
goldfinch.egg-info/dependency_links.txt
goldfinch.egg-info/top_level.txt
goldfinch.egg-info/zip-safe