Metadata-Version: 1.0
Name: goldfinch
Version: 0.3.1
Summary: Use to make sure that filenames will always be valid
Home-page: https://github.com/PerAkeMattias/goldfinch
Author: Per Ake Mattias
Author-email: PerAkeMattias@gmail.com
License: MIT
Platform: UNKNOWN
